shadowsocksr_tools/__init__.py
shadowsocksr_tools/errors.py
shadowsocksr_tools/ssr.py
shadowsocksr_tools-1.3.3.dist-info/LICENSE
shadowsocksr_tools-1.3.3.dist-info/METADATA
shadowsocksr_tools-1.3.3.dist-info/WHEEL
shadowsocksr_tools-1.3.3.dist-info/top_level.txt
shadowsocksr_tools-1.3.3.dist-info/RECORD
