Metadata-Version: 2.1
Name: shadowsocksr-tools
Version: 1.3.3
Summary: Python Shadowsocksr tools.
Home-page: https://github.com/voken100g/python-shadowsocksr-tools.git
Author: Vision Network
Author-email: michael@vision.network
License: UNKNOWN
Keywords: Proxy,Shadowsocks,Shadowsocksr,IP,GEO_IP
Platform: UNKNOWN
Classifier: Programming Language :: Python :: 3
Classifier: License :: OSI Approved :: MIT License
Classifier: Operating System :: OS Independent
Requires-Dist: requests-cache
Requires-Dist: ip-query
Requires-Dist: qwert
Requires-Dist: cli-print
Requires-Dist: proxy-fn
Requires-Dist: common-patterns
